pclick/Messaging_pb2.py
pclick/__init__.py
pclick/client.py
pclick/demo/__init__.py
pclick/demo/client.py
pclick/demo/server.py
pclick/message_proto_helpers.py
pclick/server.py
pclick-0.5.13.dist-info/METADATA
pclick-0.5.13.dist-info/WHEEL
pclick-0.5.13.dist-info/RECORD
