Metadata-Version: 2.1
Name: pclick
Version: 0.5.13
Summary: Controller to AGX Dynamics messaging
Home-page: https://github.com/algoryx/click-mirror
License: Apache-2.0
Author: Algoryx Simulation
Author-email: contact@algoryx.se
Requires-Python: >=3.8
Classifier: License :: OSI Approved :: Apache Software License
Classifier: Programming Language :: Python :: 3
Classifier: Programming Language :: Python :: 3.8
Classifier: Programming Language :: Python :: 3.9
Classifier: Programming Language :: Python :: 3.10
Classifier: Programming Language :: Python :: 3.11
Classifier: Programming Language :: Python :: 3.12
Classifier: Programming Language :: Python :: 3.13
Requires-Dist: protobuf (==4.21.12)
Requires-Dist: pyzmq (==26.2.0)
Project-URL: Repository, https://github.com/algoryx/click-mirror
